autotiktokuploader/___init__.py
autotiktokuploader/function.py
autotiktokuploader-0.2.dist-info/LICENSE.md
autotiktokuploader-0.2.dist-info/METADATA
autotiktokuploader-0.2.dist-info/WHEEL
autotiktokuploader-0.2.dist-info/top_level.txt
autotiktokuploader-0.2.dist-info/RECORD
