Metadata-Version: 2.1
Name: autotiktokuploader
Version: 0.2
Summary: Upload or schedules videos to tiktok with tiktok sounds and hashtags that work.
Home-page: https://github.com/haziq-exe/TikTokAutoUploader
Author: HAZIQ KHALID
Author-email: haziqmk123@gmail.com
Keywords: tiktok,autoupload,tiktokautoupload
Classifier: Programming Language :: Python :: 3
Classifier: Programming Language :: Python :: 3.8
Classifier: Programming Language :: Python :: 3.9
Classifier: Programming Language :: Python :: 3.10
Classifier: Programming Language :: Python :: 3.11
Classifier: License :: OSI Approved :: MIT License
Classifier: Operating System :: OS Independent
Requires-Python: >=3.6
License-File: LICENSE.md
Requires-Dist: playwright >=1.0.0
Requires-Dist: requests >=2.0.0
Requires-Dist: Pillow >=8.0.0
Requires-Dist: transformers >=4.0.0
Requires-Dist: torch >=1.0.0
Requires-Dist: scikit-learn >=0.24.0
